<annotation>
	<folder>my-project-name</folder>
	<filename>pisang_ijo_00000157.jpg</filename>
	<path>/my-project-name/pisang_ijo_00000157.jpg</path>
	<source>
		<database>Unspecified</database>
	</source>
	<size>
		<width>1920</width>
		<height>1080</height>
		<depth>3</depth>
	</size>
	<object>
		<name>pisang_ijo</name>
		<pose>Unspecified</pose>
		<truncated>Unspecified</truncated>
		<difficult>Unspecified</difficult>
		<bndbox>
			<xmin>722</xmin>
			<ymin>650</ymin>
			<xmax>937</xmax>
			<ymax>901</ymax>
		</bndbox>
	</object>
</annotation>