<annotation>
	<folder>my-project-name</folder>
	<filename>sambal_0005.jpg</filename>
	<path>/my-project-name/sambal_0005.jpg</path>
	<source>
		<database>Unspecified</database>
	</source>
	<size>
		<width>1200</width>
		<height>869</height>
		<depth>3</depth>
	</size>
	<object>
		<name>sambal</name>
		<pose>Unspecified</pose>
		<truncated>Unspecified</truncated>
		<difficult>Unspecified</difficult>
		<bndbox>
			<xmin>313</xmin>
			<ymin>227</ymin>
			<xmax>1093</xmax>
			<ymax>773</ymax>
		</bndbox>
	</object>
</annotation>